{
  "signals": [
    {
      "symbol": "BTCUSDT",
      "interval": "1h",
      "signal": "SELL",
      "entry_price": 105441.87,
      "current_price": 105492.78,
      "stop_loss": 105566.105,
      "take_profit": 105255.51749999999,
      "pattern": null,
      "score": 1,
      "trend": "BULLISH",
      "confidence": 60,
      "timestamp": "2025-06-08T02:42:00",
      "decision_factors": {
        "candlestick_pattern": {
          "name": null,
          "score": 0,
          "signal": "NEUTRAL",
          "reasoning": "No significant pattern detected",
          "weight": 0
        },
        "trend_analysis": {
          "trend": "bearish",
          "signal": "SELL",
          "reasoning": "Bearish trend detected",
          "weight": -1
        },
        "momentum_strength": {
          "strength": "strong",
          "signal": "SELL",
          "reasoning": "Strong momentum supporting bearish trend",
          "weight": -1
        },
        "rsi_analysis": {
          "value": 54.28011376379064,
          "signal": "NEUTRAL",
          "reasoning": "Professional RSI neutral at 54.3",
          "weight": 0
        },
        "macd_analysis": {
          "value": 275.11633718440135,
          "signal": "NEUTRAL",
          "reasoning": "Professional MACD neutral (MACD: 275.116, Histogram: -54.221)",
          "weight": 0
        },
        "volume_analysis": {
          "signal": "NEUTRAL",
          "reasoning": "Professional volume analysis: normal volume (0.0M)",
          "weight": 0
        },
        "support_resistance": {
          "signal": "SELL",
          "reasoning": "Price near support, potential breakdown",
          "weight": -1
        }
      },
      "total_score": -1,
      "professional_indicators": {
        "rsi": {
          "value": 54.28011376379064,
          "signal": "NEUTRAL",
          "overbought": "False",
          "oversold": "False",
          "divergence": "True"
        },
        "macd": {
          "macd": 275.11633718440135,
          "signal": 329.3377552367301,
          "histogram": -54.22141805232877,
          "signal_type": "NEUTRAL",
          "bullish_crossover": "False",
          "bearish_crossover": "False"
        },
        "bollinger_bands": {
          "upper": 106053.18789809097,
          "middle": 105424.11750000001,
          "lower": 104795.04710190905,
          "width": 1.1934088954379156,
          "percent_b": 0.514110106002334,
          "squeeze": "False",
          "breakout": "NONE"
        },
        "moving_averages": {
          "sma_20": 105424.11750000001,
          "sma_50": 104579.0248,
          "ema_12": 105535.7083718457,
          "ema_26": 105260.5920346613,
          "trend": "BULLISH",
          "golden_cross": "False",
          "death_cross": "False"
        },
        "adx": {
          "value": 31.791205180260658,
          "strength": "STRONG",
          "trend_direction": "BULLISH",
          "trending": "True"
        },
        "stochastic": {
          "k": 26.219924630398598,
          "d": 49.350324477565515,
          "signal": "NEUTRAL",
          "overbought": "False",
          "oversold": "False"
        },
        "volume": {
          "current": 301.18228,
          "sma": 343.57229500000005,
          "vwap": 105595.92970442477,
          "obv": 6673.955709999999,
          "volume_trend": "NORMAL",
          "high_volume": "False"
        },
        "market_assessment": {
          "trend": "BULLISH",
          "momentum": "BEARISH",
          "volatility": "HIGH",
          "volume_confirmation": "False",
          "signal_strength": 2
        }
      },
      "id": 1
    },
    {
      "symbol": "ETHUSDT",
      "interval": "1h",
      "signal": "SELL",
      "entry_price": 2511.68,
      "current_price": 2511.93,
      "stop_loss": 2515.3149999999996,
      "take_profit": 2506.2275,
      "pattern": "Bearish Engulfing",
      "score": 2,
      "trend": "BULLISH",
      "confidence": 70,
      "timestamp": "2025-06-08T02:02:00",
      "decision_factors": {
        "candlestick_pattern": {
          "name": "Bearish Engulfing",
          "score": 4,
          "signal": "SELL",
          "reasoning": "Strong bearish pattern: Bearish Engulfing",
          "weight": -2
        },
        "trend_analysis": {
          "trend": "bearish",
          "signal": "SELL",
          "reasoning": "Bearish trend detected",
          "weight": -1
        },
        "momentum_strength": {
          "strength": "strong",
          "signal": "SELL",
          "reasoning": "Strong momentum supporting bearish trend",
          "weight": -1
        },
        "rsi_analysis": {
          "value": 51.51999001980369,
          "signal": "NEUTRAL",
          "reasoning": "Professional RSI neutral at 51.5",
          "weight": 0
        },
        "macd_analysis": {
          "value": 6.878162113592225,
          "signal": "NEUTRAL",
          "reasoning": "Professional MACD neutral (MACD: 6.878, Histogram: 0.003)",
          "weight": 0
        },
        "volume_analysis": {
          "signal": "NEUTRAL",
          "reasoning": "Professional volume analysis: normal volume (0.0M)",
          "weight": 0
        },
        "support_resistance": {
          "signal": "SELL",
          "reasoning": "Price near support, potential breakdown",
          "weight": -1
        }
      },
      "total_score": -2,
      "professional_indicators": {
        "rsi": {
          "value": 51.51999001980369,
          "signal": "NEUTRAL",
          "overbought": "False",
          "oversold": "False",
          "divergence": "True"
        },
        "macd": {
          "macd": 6.878162113592225,
          "signal": 6.874961442208386,
          "histogram": 0.003200671383838838,
          "signal_type": "NEUTRAL",
          "bullish_crossover": "False",
          "bearish_crossover": "False"
        },
        "bollinger_bands": {
          "upper": 2537.1322897796877,
          "middle": 2509.8514999999998,
          "lower": 2482.570710220312,
          "width": 2.17389672494073,
          "percent_b": 0.5335125928311925,
          "squeeze": "False",
          "breakout": "NONE"
        },
        "moving_averages": {
          "sma_20": 2509.8514999999998,
          "sma_50": 2491.3918,
          "ema_12": 2516.168978899052,
          "ema_26": 2509.29081678546,
          "trend": "BULLISH",
          "golden_cross": "False",
          "death_cross": "False"
        },
        "adx": {
          "value": 25.7776002804786,
          "strength": "STRONG",
          "trend_direction": "BULLISH",
          "trending": "True"
        },
        "stochastic": {
          "k": 36.60523763336532,
          "d": 45.02424830261873,
          "signal": "NEUTRAL",
          "overbought": "False",
          "oversold": "False"
        },
        "volume": {
          "current": 8623.6211,
          "sma": 10226.246875,
          "vwap": 2517.951006820943,
          "obv": 41794.19900000002,
          "volume_trend": "NORMAL",
          "high_volume": "False"
        },
        "market_assessment": {
          "trend": "BULLISH",
          "momentum": "NEUTRAL",
          "volatility": "HIGH",
          "volume_confirmation": "False",
          "signal_strength": 2
        }
      },
      "id": 2
    },
    {
      "symbol": "BNBUSDT",
      "interval": "1h",
      "signal": "SELL",
      "entry_price": 649.61,
      "current_price": 649.88,
      "stop_loss": 650.4300000000001,
      "take_profit": 648.38,
      "pattern": "Bearish Engulfing",
      "score": 2,
      "trend": "BEARISH",
      "confidence": 70,
      "timestamp": "2025-06-08T02:46:00",
      "decision_factors": {
        "candlestick_pattern": {
          "name": "Bearish Engulfing",
          "score": 4,
          "signal": "SELL",
          "reasoning": "Strong bearish pattern: Bearish Engulfing",
          "weight": -2
        },
        "trend_analysis": {
          "trend": "bearish",
          "signal": "SELL",
          "reasoning": "Bearish trend detected",
          "weight": -1
        },
        "momentum_strength": {
          "strength": "weak",
          "signal": "NEUTRAL",
          "reasoning": "Weak momentum detected",
          "weight": 0
        },
        "rsi_analysis": {
          "value": 50.443133461748054,
          "signal": "NEUTRAL",
          "reasoning": "Professional RSI neutral at 50.4",
          "weight": 0
        },
        "macd_analysis": {
          "value": 0.9852692399705347,
          "signal": "NEUTRAL",
          "reasoning": "Professional MACD neutral (MACD: 0.985, Histogram: -0.208)",
          "weight": 0
        },
        "volume_analysis": {
          "signal": "NEUTRAL",
          "reasoning": "Professional volume analysis: low volume (0.0M)",
          "weight": 0
        },
        "support_resistance": {
          "signal": "NEUTRAL",
          "reasoning": "Price in middle range",
          "weight": 0
        }
      },
      "total_score": -2,
      "professional_indicators": {
        "rsi": {
          "value": 50.443133461748054,
          "signal": "NEUTRAL",
          "overbought": "False",
          "oversold": "False",
          "divergence": "True"
        },
        "macd": {
          "macd": 0.9852692399705347,
          "signal": 1.1928179976812383,
          "histogram": -0.20754875771070358,
          "signal_type": "NEUTRAL",
          "bullish_crossover": "False",
          "bearish_crossover": "False"
        },
        "bollinger_bands": {
          "upper": 653.4114390832582,
          "middle": 650.077,
          "lower": 646.7425609167418,
          "width": 1.0258597314651001,
          "percent_b": 0.42997322962882506,
          "squeeze": "False",
          "breakout": "NONE"
        },
        "moving_averages": {
          "sma_20": 650.077,
          "sma_50": 646.487,
          "ema_12": 650.5308092103113,
          "ema_26": 649.5455399703408,
          "trend": "NEUTRAL",
          "golden_cross": "False",
          "death_cross": "False"
        },
        "adx": {
          "value": 12.542717659429579,
          "strength": "WEAK",
          "trend_direction": "BEARISH",
          "trending": "False"
        },
        "stochastic": {
          "k": 17.808219178081917,
          "d": 32.18735764810179,
          "signal": "NEUTRAL",
          "overbought": "False",
          "oversold": "True"
        },
        "volume": {
          "current": 1616.476,
          "sma": 3349.19125,
          "vwap": 650.807110770322,
          "obv": 10040.64799999995,
          "volume_trend": "LOW",
          "high_volume": "False"
        },
        "market_assessment": {
          "trend": "BEARISH",
          "momentum": "BEARISH",
          "volatility": "HIGH",
          "volume_confirmation": "False",
          "signal_strength": 0
        }
      },
      "id": 3
    },
    {
      "symbol": "ADAUSDT",
      "interval": "1h",
      "signal": "SELL",
      "entry_price": 0.6588,
      "current_price": 0.6571,
      "stop_loss": 0.6611,
      "take_profit": 0.65535,
      "pattern": "Bearish Engulfing",
      "score": 2,
      "trend": "BEARISH",
      "confidence": 70,
      "timestamp": "2025-06-08T02:33:00",
      "decision_factors": {
        "candlestick_pattern": {
          "name": "Bearish Engulfing",
          "score": 4,
          "signal": "SELL",
          "reasoning": "Strong bearish pattern: Bearish Engulfing",
          "weight": -2
        },
        "trend_analysis": {
          "trend": "bearish",
          "signal": "SELL",
          "reasoning": "Bearish trend detected",
          "weight": -1
        },
        "momentum_strength": {
          "strength": "weak",
          "signal": "NEUTRAL",
          "reasoning": "Weak momentum detected",
          "weight": 0
        },
        "rsi_analysis": {
          "value": 43.45073413782009,
          "signal": "NEUTRAL",
          "reasoning": "Professional RSI neutral at 43.5",
          "weight": 0
        },
        "macd_analysis": {
          "value": 0.0001899776387974672,
          "signal": "NEUTRAL",
          "reasoning": "Professional MACD neutral (MACD: 0.000, Histogram: -0.001)",
          "weight": 0
        },
        "volume_analysis": {
          "signal": "NEUTRAL",
          "reasoning": "Professional volume analysis: normal volume (1.8M)",
          "weight": 0
        },
        "support_resistance": {
          "signal": "SELL",
          "reasoning": "Bollinger Bands lower breakout (BB%: -0.01)",
          "weight": -1
        }
      },
      "total_score": -2,
      "professional_indicators": {
        "rsi": {
          "value": 43.45073413782009,
          "signal": "NEUTRAL",
          "overbought": "False",
          "oversold": "False",
          "divergence": "False"
        },
        "macd": {
          "macd": 0.0001899776387974672,
          "signal": 0.0012790904581571627,
          "histogram": -0.0010891128193596955,
          "signal_type": "NEUTRAL",
          "bullish_crossover": "False",
          "bearish_crossover": "False"
        },
        "bollinger_bands": {
          "upper": 0.6714249601909594,
          "middle": 0.665145,
          "lower": 0.6588650398090405,
          "width": 1.8882980976958241,
          "percent_b": -0.0051783615709953676,
          "squeeze": "False",
          "breakout": "LOWER"
        },
        "moving_averages": {
          "sma_20": 0.665145,
          "sma_50": 0.6582640000000001,
          "ema_12": 0.6632403357964543,
          "ema_26": 0.6630503581576568,
          "trend": "NEUTRAL",
          "golden_cross": "False",
          "death_cross": "False"
        },
        "adx": {
          "value": 14.665395566897411,
          "strength": "WEAK",
          "trend_direction": "BEARISH",
          "trending": "False"
        },
        "stochastic": {
          "k": 20.805369127517434,
          "d": 21.743070062373516,
          "signal": "NEUTRAL",
          "overbought": "False",
          "oversold": "False"
        },
        "volume": {
          "current": 1792164.0,
          "sma": 2117191.085,
          "vwap": 0.6644726043738813,
          "obv": -43044652.99999999,
          "volume_trend": "NORMAL",
          "high_volume": "False"
        },
        "market_assessment": {
          "trend": "BEARISH",
          "momentum": "BEARISH",
          "volatility": "HIGH",
          "volume_confirmation": "False",
          "signal_strength": 0
        }
      },
      "id": 4
    },
    {
      "symbol": "SOLUSDT",
      "interval": "1h",
      "signal": "SELL",
      "entry_price": 149.75,
      "current_price": 149.83,
      "stop_loss": 150.08499999999998,
      "take_profit": 149.2475,
      "pattern": null,
      "score": 2,
      "trend": "BEARISH",
      "confidence": 70,
      "timestamp": "2025-06-08T02:19:00",
      "decision_factors": {
        "candlestick_pattern": {
          "name": null,
          "score": 0,
          "signal": "NEUTRAL",
          "reasoning": "No significant pattern detected",
          "weight": 0
        },
        "trend_analysis": {
          "trend": "bearish",
          "signal": "SELL",
          "reasoning": "Bearish trend detected",
          "weight": -1
        },
        "momentum_strength": {
          "strength": "strong",
          "signal": "SELL",
          "reasoning": "Strong momentum supporting bearish trend",
          "weight": -1
        },
        "rsi_analysis": {
          "value": 44.97818907602288,
          "signal": "NEUTRAL",
          "reasoning": "Professional RSI neutral at 45.0",
          "weight": 0
        },
        "macd_analysis": {
          "value": -0.0032328986711434027,
          "signal": "NEUTRAL",
          "reasoning": "Professional MACD neutral (MACD: -0.003, Histogram: -0.221)",
          "weight": 0
        },
        "volume_analysis": {
          "signal": "NEUTRAL",
          "reasoning": "Professional volume analysis: normal volume (0.1M)",
          "weight": 0
        },
        "support_resistance": {
          "signal": "SELL",
          "reasoning": "Price near support, potential breakdown",
          "weight": -1
        }
      },
      "total_score": -2,
      "professional_indicators": {
        "rsi": {
          "value": 44.97818907602288,
          "signal": "NEUTRAL",
          "overbought": "False",
          "oversold": "False",
          "divergence": "False"
        },
        "macd": {
          "macd": -0.0032328986711434027,
          "signal": 0.21737960792412273,
          "histogram": -0.22061250659526613,
          "signal_type": "NEUTRAL",
          "bullish_crossover": "False",
          "bearish_crossover": "False"
        },
        "bollinger_bands": {
          "upper": 152.5850831179972,
          "middle": 151.02100000000002,
          "lower": 149.45691688200284,
          "width": 2.0713452009947906,
          "percent_b": 0.09369166977917803,
          "squeeze": "False",
          "breakout": "NONE"
        },
        "moving_averages": {
          "sma_20": 151.02100000000002,
          "sma_50": 149.71640000000002,
          "ema_12": 150.43512131701343,
          "ema_26": 150.43835421568457,
          "trend": "NEUTRAL",
          "golden_cross": "False",
          "death_cross": "False"
        },
        "adx": {
          "value": 15.530307918740089,
          "strength": "WEAK",
          "trend_direction": "BEARISH",
          "trending": "False"
        },
        "stochastic": {
          "k": 18.34862385321094,
          "d": 20.532034114004606,
          "signal": "NEUTRAL",
          "overbought": "False",
          "oversold": "True"
        },
        "volume": {
          "current": 55193.833,
          "sma": 57086.30850000001,
          "vwap": 150.78365936671136,
          "obv": 104655.75499999982,
          "volume_trend": "NORMAL",
          "high_volume": "False"
        },
        "market_assessment": {
          "trend": "BEARISH",
          "momentum": "BEARISH",
          "volatility": "HIGH",
          "volume_confirmation": "False",
          "signal_strength": 0
        }
      },
      "id": 5
    },
    {
      "symbol": "DOTUSDT",
      "interval": "1h",
      "signal": "SELL",
      "entry_price": 4.024,
      "current_price": 4.022,
      "stop_loss": 4.032,
      "take_profit": 4.0120000000000005,
      "pattern": null,
      "score": 1,
      "trend": "NEUTRAL",
      "confidence": 60,
      "timestamp": "2025-06-08T02:07:00",
      "decision_factors": {
        "candlestick_pattern": {
          "name": null,
          "score": 0,
          "signal": "NEUTRAL",
          "reasoning": "No significant pattern detected",
          "weight": 0
        },
        "trend_analysis": {
          "trend": "bearish",
          "signal": "SELL",
          "reasoning": "Bearish trend detected",
          "weight": -1
        },
        "momentum_strength": {
          "strength": "strong",
          "signal": "SELL",
          "reasoning": "Strong momentum supporting bearish trend",
          "weight": -1
        },
        "rsi_analysis": {
          "value": 54.773353817743235,
          "signal": "NEUTRAL",
          "reasoning": "Professional RSI neutral at 54.8",
          "weight": 0
        },
        "macd_analysis": {
          "value": 0.016477387625053908,
          "signal": "NEUTRAL",
          "reasoning": "Professional MACD neutral (MACD: 0.016, Histogram: -0.003)",
          "weight": 0
        },
        "volume_analysis": {
          "signal": "NEUTRAL",
          "reasoning": "Professional volume analysis: normal volume (0.1M)",
          "weight": 0
        },
        "support_resistance": {
          "signal": "SELL",
          "reasoning": "Price near support, potential breakdown",
          "weight": -1
        }
      },
      "total_score": -1,
      "professional_indicators": {
        "rsi": {
          "value": 54.773353817743235,
          "signal": "NEUTRAL",
          "overbought": "False",
          "oversold": "False",
          "divergence": "False"
        },
        "macd": {
          "macd": 0.016477387625053908,
          "signal": 0.019609286964281304,
          "histogram": -0.0031318993392273967,
          "signal_type": "NEUTRAL",
          "bullish_crossover": "False",
          "bearish_crossover": "False"
        },
        "bollinger_bands": {
          "upper": 4.05191772821625,
          "middle": 4.02575,
          "lower": 3.9995822717837504,
          "width": 1.3000175478482279,
          "percent_b": 0.46656186609822664,
          "squeeze": "False",
          "breakout": "NONE"
        },
        "moving_averages": {
          "sma_20": 4.02575,
          "sma_50": 3.9649400000000004,
          "ema_12": 4.025160455162123,
          "ema_26": 4.008683067537069,
          "trend": "NEUTRAL",
          "golden_cross": "False",
          "death_cross": "False"
        },
        "adx": {
          "value": 25.742050450642434,
          "strength": "STRONG",
          "trend_direction": "BULLISH",
          "trending": "True"
        },
        "stochastic": {
          "k": 37.037037037037706,
          "d": 43.209876543210385,
          "signal": "NEUTRAL",
          "overbought": "False",
          "oversold": "False"
        },
        "volume": {
          "current": 50903.33,
          "sma": 80399.591,
          "vwap": 4.031189472455946,
          "obv": -2398356.5500000003,
          "volume_trend": "NORMAL",
          "high_volume": "False"
        },
        "market_assessment": {
          "trend": "NEUTRAL",
          "momentum": "BEARISH",
          "volatility": "HIGH",
          "volume_confirmation": "False",
          "signal_strength": 1
        }
      },
      "id": 6
    }
  ],
  "last_updated": "2025-06-08T06:29:33.959169"
}